tima/__init__.py
tima/backtest.py
tima/datasets.py
tima-0.0.1.dist-info/LICENSE
tima-0.0.1.dist-info/METADATA
tima-0.0.1.dist-info/WHEEL
tima-0.0.1.dist-info/top_level.txt
tima-0.0.1.dist-info/RECORD
