Metadata-Version: 2.1
Name: tima
Version: 0.0.1
Summary: Time-series forecast In Machine-learning Algorithms
Home-page: UNKNOWN
Author: ['Wenting Tu']
License: UNKNOWN
Platform: UNKNOWN
License-File: LICENSE
